djangocms_admin_style/__init__.py
djangocms_admin_style/models.py
djangocms_admin_style/locale/de/LC_MESSAGES/django.mo
djangocms_admin_style/locale/de/LC_MESSAGES/django.po
djangocms_admin_style/locale/en/LC_MESSAGES/django.mo
djangocms_admin_style/locale/en/LC_MESSAGES/django.po
djangocms_admin_style/locale/es/LC_MESSAGES/django.mo
djangocms_admin_style/locale/es/LC_MESSAGES/django.po
djangocms_admin_style/locale/fr/LC_MESSAGES/django.mo
djangocms_admin_style/locale/fr/LC_MESSAGES/django.po
djangocms_admin_style/locale/it/LC_MESSAGES/django.mo
djangocms_admin_style/locale/it/LC_MESSAGES/django.po
djangocms_admin_style/locale/lt/LC_MESSAGES/django.mo
djangocms_admin_style/locale/lt/LC_MESSAGES/django.po
djangocms_admin_style/locale/ru/LC_MESSAGES/django.mo
djangocms_admin_style/locale/ru/LC_MESSAGES/django.po
djangocms_admin_style/locale/uk/LC_MESSAGES/django.mo
djangocms_admin_style/locale/uk/LC_MESSAGES/django.po
djangocms_admin_style/sass/djangocms-admin.scss
djangocms_admin_style/sass/components/_base.scss
djangocms_admin_style/sass/components/_changelist.scss
djangocms_admin_style/sass/components/_cms-update.scss
djangocms_admin_style/sass/components/_cmsplaceholders.scss
djangocms_admin_style/sass/components/_content.scss
djangocms_admin_style/sass/components/_dashboard.scss
djangocms_admin_style/sass/components/_dialog.scss
djangocms_admin_style/sass/components/_django-nested-admin.scss
djangocms_admin_style/sass/components/_drag-and-drop.scss
djangocms_admin_style/sass/components/_filer.scss
djangocms_admin_style/sass/components/_footer.scss
djangocms_admin_style/sass/components/_forms.scss
djangocms_admin_style/sass/components/_header.scss
djangocms_admin_style/sass/components/_iconography.scss
djangocms_admin_style/sass/components/_icons.scss
djangocms_admin_style/sass/components/_login.scss
djangocms_admin_style/sass/components/_messages.scss
djangocms_admin_style/sass/components/_mobile.scss
djangocms_admin_style/sass/components/_modal.scss
djangocms_admin_style-3.2.7.dist-info/LICENSE
djangocms_admin_style-3.2.7.dist-info/METADATA
djangocms_admin_style-3.2.7.dist-info/WHEEL
djangocms_admin_style-3.2.7.dist-info/top_level.txt
djangocms_admin_style-3.2.7.dist-info/RECORD
