Metadata-Version: 2.1
Name: djangocms-admin-style
Version: 3.2.7
Summary: Adds pretty CSS styles for the django CMS admin interface.
Home-page: https://github.com/django-cms/djangocms-admin-style
Author: Divio AG
Author-email: info@divio.ch
Maintainer: Django CMS Association and contributors
Maintainer-email: info@django-cms.org
License: BSD-3-Clause
Classifier: Development Status :: 5 - Production/Stable
Classifier: Environment :: Web Environment
Classifier: Intended Audience :: Developers
Classifier: License :: OSI Approved :: BSD License
Classifier: Operating System :: OS Independent
Classifier: Programming Language :: Python
Classifier: Programming Language :: Python :: 3
Classifier: Programming Language :: Python :: 3.7
Classifier: Programming Language :: Python :: 3.8
Classifier: Programming Language :: Python :: 3.9
Classifier: Programming Language :: Python :: 3.10
Classifier: Programming Language :: Python :: 3.11
Classifier: Framework :: Django
Classifier: Framework :: Django :: 2.2
Classifier: Framework :: Django :: 3.1
Classifier: Framework :: Django :: 3.2
Classifier: Framework :: Django :: 4.0
Classifier: Framework :: Django :: 4.1
Classifier: Framework :: Django :: 4.2
Classifier: Framework :: Django :: 5.0
Classifier: Framework :: Django CMS
Classifier: Framework :: Django CMS :: 3.6
Classifier: Framework :: Django CMS :: 3.7
Classifier: Framework :: Django CMS :: 3.8
Classifier: Framework :: Django CMS :: 3.8
Classifier: Framework :: Django CMS :: 3.9
Classifier: Framework :: Django CMS :: 3.10
Classifier: Framework :: Django CMS :: 3.11
Classifier: Framework :: Django CMS :: 4.0
Classifier: Framework :: Django CMS :: 4.1
Classifier: Topic :: Internet :: WWW/HTTP
Classifier: Topic :: Internet :: WWW/HTTP :: Dynamic Content
Classifier: Topic :: Software Development
Classifier: Topic :: Software Development :: Libraries
Requires-Python: >=3.7
License-File: LICENSE
Requires-Dist: Django
